CHANGES.txt
CONTRIBUTORS.txt
MANIFEST.in
README.txt
setup.cfg
setup.py
collective/.DS_Store
collective/__init__.py
collective.exhibit.egg-info/PKG-INFO
collective.exhibit.egg-info/SOURCES.txt
collective.exhibit.egg-info/dependency_links.txt
collective.exhibit.egg-info/entry_points.txt
collective.exhibit.egg-info/namespace_packages.txt
collective.exhibit.egg-info/not-zip-safe
collective.exhibit.egg-info/paster_plugins.txt
collective.exhibit.egg-info/requires.txt
collective.exhibit.egg-info/top_level.txt
collective/exhibit/.DS_Store
collective/exhibit/__init__.py
collective/exhibit/config.py
collective/exhibit/configure.zcml
collective/exhibit/interfaces.py
collective/exhibit/permissions.zcml
collective/exhibit/profile.zcml
collective/exhibit/setuphandlers.py
collective/exhibit/testing.py
collective/exhibit/browser/__init__.py
collective/exhibit/browser/configure.zcml
collective/exhibit/browser/controlpanel.py
collective/exhibit/browser/exhibit.pt
collective/exhibit/browser/exhibititem.py
collective/exhibit/browser/exhibits.css
collective/exhibit/browser/exhibitsection_gallery.pt
collective/exhibit/browser/faceted-item.pt
collective/exhibit/browser/helpers.py
collective/exhibit/browser/types_panel.pt
collective/exhibit/browser/exhibititem_templates/view.pt
collective/exhibit/browser/images/ExhibitIcon.png
collective/exhibit/browser/images/ExhibitItemIcon.png
collective/exhibit/browser/images/ExhibitSectionIcon.png
collective/exhibit/browser/images/exhibit-lessinfo.png
collective/exhibit/browser/images/exhibit-moreinfo.png
collective/exhibit/browser/images/exhibitsection.png
collective/exhibit/browser/images/tooltip_bg.png
collective/exhibit/content/__init__.py
collective/exhibit/content/configure.zcml
collective/exhibit/content/exhibit.py
collective/exhibit/content/exhibititem.py
collective/exhibit/content/exhibitsection.py
collective/exhibit/portlets/__init__.py
collective/exhibit/portlets/configure.zcml
collective/exhibit/portlets/interfaces.py
collective/exhibit/portlets/navigation.pt
collective/exhibit/portlets/navigation.py
collective/exhibit/profiles/.DS_Store
collective/exhibit/profiles/default/catalog.xml
collective/exhibit/profiles/default/collective-exhibit.txt
collective/exhibit/profiles/default/controlpanel.xml
collective/exhibit/profiles/default/cssregistry.xml
collective/exhibit/profiles/default/ex_bibliography_facets.xml
