Metadata-Version: 1.1
Name: collective.exhibit
Version: 1.0a1
Summary: Content product for creating multi-section exhibits for museums and similar sites
Home-page: https://github.com/jazkarta/collective.exhibit
Author: jazkarta
Author-email: info@jazkarta.com
License: GPL
Platform: UNKNOWN
Classifier: Framework :: Plone
Classifier: Intended Audience :: Developers
